biosutilities/__init__.py
biosutilities/__main__.py
biosutilities/ami_pfat_extract.py
biosutilities/ami_ucp_extract.py
biosutilities/apple_efi_id.py
biosutilities/apple_efi_im4p.py
biosutilities/apple_efi_pbzx.py
biosutilities/apple_efi_pkg.py
biosutilities/award_bios_extract.py
biosutilities/dell_pfs_extract.py
biosutilities/fujitsu_sfx_extract.py
biosutilities/fujitsu_upc_extract.py
biosutilities/insyde_ifd_extract.py
biosutilities/panasonic_bios_extract.py
biosutilities/phoenix_tdk_extract.py
biosutilities/portwell_efi_extract.py
biosutilities/toshiba_com_extract.py
biosutilities/vaio_package_extract.py
biosutilities/common/checksums.py
biosutilities/common/compression.py
biosutilities/common/executables.py
biosutilities/common/externals.py
biosutilities/common/paths.py
biosutilities/common/patterns.py
biosutilities/common/structs.py
biosutilities/common/system.py
biosutilities/common/templates.py
biosutilities/common/texts.py
biosutilities-25.7.1.dist-info/licenses/LICENSE
biosutilities-25.7.1.dist-info/METADATA
biosutilities-25.7.1.dist-info/WHEEL
biosutilities-25.7.1.dist-info/entry_points.txt
biosutilities-25.7.1.dist-info/top_level.txt
biosutilities-25.7.1.dist-info/RECORD
