Metadata-Version: 2.4
Name: biosutilities
Version: 25.7.1
Summary: Various BIOS Utilities for Modding/Research
Author: Plato Mavropoulos
Maintainer: Plato Mavropoulos
License-Expression: BSD-2-Clause-Patent
Project-URL: Homepage, https://github.com/platomav/BIOSUtilities
Project-URL: Repository, https://github.com/platomav/BIOSUtilities
Project-URL: Issues, https://github.com/platomav/BIOSUtilities/issues
Project-URL: Readme, https://github.com/platomav/BIOSUtilities/blob/main/README.md
Project-URL: Changelog, https://github.com/platomav/BIOSUtilities/blob/main/CHANGELOG
Keywords: bios,uefi,firmware,extract,unpack,package,ami,insyde,phoenix,award,apple,dell,fujitsu,panasonic,toshiba,dynabook,vaio,portwell,bios guard,pfat,ucp,im4p,pbzx,efi,pfs,sfx,upc,iflash,ifdpacker,ifd,com
Classifier: Programming Language :: Python :: 3.10
Classifier: Programming Language :: Python :: 3.11
Classifier: Programming Language :: Python :: 3.12
Classifier: Programming Language :: Python :: 3.13
Classifier: Operating System :: Microsoft :: Windows
Classifier: Operating System :: POSIX :: Linux
Classifier: Operating System :: MacOS
Classifier: Topic :: Security
Classifier: Topic :: Scientific/Engineering :: Information Analysis
Requires-Python: >=3.10
License-File: LICENSE
Provides-Extra: lznt1
Requires-Dist: dissect.util==3.20; extra == "lznt1"
Provides-Extra: pefile
Requires-Dist: pefile==2023.2.7; extra == "pefile"
Dynamic: license-file
